pathshandler/__init__.py
pathshandler/paths_config.json
pathshandler/pathshandler.py
pathshandler-0.0.2.dist-info/LICENSE
pathshandler-0.0.2.dist-info/METADATA
pathshandler-0.0.2.dist-info/WHEEL
pathshandler-0.0.2.dist-info/top_level.txt
pathshandler-0.0.2.dist-info/RECORD
