Metadata-Version: 2.2
Name: pathshandler
Version: 0.0.2
Summary: Package to manipulate paths
Author: Gauthier Patin
Author-email: Gauthier Patin <g.patin@monemail.com>
License:                     GNU GENERAL PUBLIC LICENSE
Project-URL: Homepage, https://github.com/g-patin/pathshandler
Keywords: paths,folders
Classifier: Programming Language :: Python :: 3
Classifier: License :: OSI Approved :: GNU General Public License v3 (GPLv3)
Classifier: Operating System :: OS Independent
Requires-Python: >=3.8
License-File: LICENSE
